[
  {
    "prefecture": "Hokkaido",
    "flower": "Hamanasu"
  },
  {
    "prefecture": "Aomoriken",
    "flower": "Ringonohana"
  },
  {
    "prefecture": "Iwateken",
    "flower": "Kiri"
  },
  {
    "prefecture": "Miyagiken",
    "flower": "Miyaginohagi"
  },
  {
    "prefecture": "Akitaken",
    "flower": "Fukinoto"
  },
  {
    "prefecture": "Yamagataken",
    "flower": "Benibana"
  },
  {
    "prefecture": "Fukushimaken",
    "flower": "Shakunage"
  },
  {
    "prefecture": "Ibarakiken",
    "flower": "Bara"
  },
  {
    "prefecture": "Tochigiken",
    "flower": "Tsutsuji"
  },
  {
    "prefecture": "Gunmaken",
    "flower": "Tsutsuji"
  },
  {
    "prefecture": "Saitamaken",
    "flower": "Sakurasou"
  },
  {
    "prefecture": "Chibaken",
    "flower": "Nanohana"
  },
  {
    "prefecture": "Tokyoto",
    "flower": "Sakura"
  },
  {
    "prefecture": "Kanagawaken",
    "flower": "Yuri"
  },
  {
    "prefecture": "Niigataken",
    "flower": "Tulips"
  },
  {
    "prefecture": "Toyamaken",
    "flower": "Tulips"
  },
  {
    "prefecture": "Ishikawaken",
    "flower": "Yuri"
  },
  {
    "prefecture": "Fukuiken",
    "flower": "Echizensuisen"
  },
  {
    "prefecture": "Yamanashiken",
    "flower": "Sakura"
  },
  {
    "prefecture": "Naganoken",
    "flower": "Rindou"
  },
  {
    "prefecture": "Gifuken",
    "flower": "Rengesou"
  },
  {
    "prefecture": "Shizuokaken",
    "flower": "Tsutsuji"
  },
  {
    "prefecture": "Aichiken",
    "flower": "Kakitsubata"
  },
  {
    "prefecture": "Mieken",
    "flower": "Hanashoubu"
  },
  {
    "prefecture": "Shigaken",
    "flower": "Shakunage"
  },
  {
    "prefecture": "Kyotofu",
    "flower": "Sakura"
  },
  {
    "prefecture": "Osakafu",
    "flower": "Ume"
  },
  {
    "prefecture": "Hyogoken",
    "flower": "Nojigiku"
  },
  {
    "prefecture": "Naraken",
    "flower": "Sakura"
  },
  {
    "prefecture": "Wakayamaken",
    "flower": "Ume"
  },
  {
    "prefecture": "Tottoriken",
    "flower": "Nashinohana"
  },
  {
    "prefecture": "Shimaneken",
    "flower": "Botan"
  },
  {
    "prefecture": "Okayamaken",
    "flower": "Momo"
  },
  {
    "prefecture": "Hiroshimaken",
    "flower": "Momiji"
  },
  {
    "prefecture": "Yamaguchiken",
    "flower": "Mikannohana"
  },
  {
    "prefecture": "Tokushimaken",
    "flower": "Sudachinohana"
  },
  {
    "prefecture": "Kagawaken",
    "flower": "Olive"
  },
  {
    "prefecture": "Ehimeken",
    "flower": "Mikannohana"
  },
  {
    "prefecture": "Kouchiken",
    "flower": "Momo"
  },
  {
    "prefecture": "Fukuokaken",
    "flower": "Ume"
  },
  {
    "prefecture": "Sagaken",
    "flower": "Kusunohana"
  },
  {
    "prefecture": "Nagasakiken",
    "flower": "Tsutsuji"
  },
  {
    "prefecture": "Kumamotoken",
    "flower": "Rindou"
  },
  {
    "prefecture": "Oitaken",
    "flower": "Ume"
  },
  {
    "prefecture": "Miyazakiken",
    "flower": "Hamayuu"
  },
  {
    "prefecture": "Kagoshimaken",
    "flower": "Miyamakirishima"
  },
  {
    "prefecture": "Okinawaken",
    "flower": "Deigo"
  }
]
